README.md
setup.cfg
setup.py
trtl/TurtleCoind.py
trtl/Utils.py
trtl/WalletAPI.py
trtl/__init__.py
trtl.egg-info/PKG-INFO
trtl.egg-info/SOURCES.txt
trtl.egg-info/dependency_links.txt
trtl.egg-info/requires.txt
trtl.egg-info/top_level.txt