Metadata-Version: 2.1
Name: trtl
Version: 0.0.2
Summary: The Python RPC Wrapper for TurtleCoind and WalletAPI.
Home-page: https://github.com/sohamb03/trtl-py
Author: Sayan Bhattacharyya
Author-email: sohamb03@outlook.com
License: MIT
Download-URL: https://github.com/sohamb03/trtl-py/archive/v_002.tar.gz
Project-URL: Documentation, https://trtl-py.sohamb03.me
Platform: UNKNOWN
Classifier: Development Status :: 4 - Beta
Classifier: Intended Audience :: Developers
Classifier: Topic :: Software Development :: Build Tools
Classifier: License :: OSI Approved :: MIT License
Classifier: Programming Language :: Python :: 3
Classifier: Programming Language :: Python :: 3.6
Classifier: Programming Language :: Python :: 3.7
Classifier: Programming Language :: Python :: 3.8
Requires-Python: >=3.6
